azllm/__init__.py
azllm/base.py
azllm/clients/__init__.py
azllm/clients/anthropic.py
azllm/clients/deepseek.py
azllm/clients/fireworks.py
azllm/clients/gemini.py
azllm/clients/grok.py
azllm/clients/ollama.py
azllm/clients/openai.py
azllm/configmanager.py
azllm/core.py
azllm/utils.py
azllm-0.1.6.dist-info/LICENSE
azllm-0.1.6.dist-info/METADATA
azllm-0.1.6.dist-info/WHEEL
azllm-0.1.6.dist-info/RECORD
