Metadata-Version: 2.3
Name: azllm
Version: 0.1.6
Summary: A Python package that provides an easier user interface for multiple LLM providers.
License: MIT
Keywords: llm,openai,ollama,grok,anthropic,deepseek,local,gemini,parallel,batch,text generation
Author: Hanif Sajid
Requires-Python: >=3.11
Classifier: License :: OSI Approved :: MIT License
Classifier: Programming Language :: Python :: 3
Classifier: Programming Language :: Python :: 3.11
Classifier: Programming Language :: Python :: 3.12
Classifier: Programming Language :: Python :: 3.13
Requires-Dist: openai (>=1.76.0,<2.0.0)
Requires-Dist: python-dotenv (>=1.1.0,<2.0.0)
Requires-Dist: pyyaml (>=6.0.2,<7.0.0)
Project-URL: Homepage, https://hanifsajid.github.io/azllm
Project-URL: Repository, https://github.com/hanifsajid/azllm
Project-URL: doucmentation, https://hanifsajid.github.io/azllm
